mip_package_manager/__init__.py
mip_package_manager/__main__.py
mip_package_manager/commands/__init__.py
mip_package_manager/commands/dependency_graph.py
mip_package_manager/commands/find_collisions.py
mip_package_manager/commands/install.py
mip_package_manager/commands/list_command.py
mip_package_manager/commands/matlab_integration.py
mip_package_manager/commands/package_info.py
mip_package_manager/commands/platform_utils.py
mip_package_manager/commands/uninstall.py
mip_package_manager/commands/utils.py
mip_package_manager/matlab/mip.m
mip_package_manager/matlab/+mip/list_loaded.m
mip_package_manager/matlab/+mip/load.m
mip_package_manager/matlab/+mip/pin.m
mip_package_manager/matlab/+mip/unload.m
mip_package_manager/matlab/+mip/unpin.m
mip_package_manager-0.3.2.dist-info/licenses/LICENSE
mip_package_manager-0.3.2.dist-info/METADATA
mip_package_manager-0.3.2.dist-info/WHEEL
mip_package_manager-0.3.2.dist-info/entry_points.txt
mip_package_manager-0.3.2.dist-info/top_level.txt
mip_package_manager-0.3.2.dist-info/RECORD
