Metadata-Version: 2.4
Name: mip-package-manager
Version: 0.3.2
Summary: pip-style package manager for MATLAB packages
Author: Jeremy Magland, Dan Fortunato
License: Apache License 2.0
Project-URL: Homepage, https://github.com/mip-org/mip
Project-URL: Repository, https://github.com/mip-org/mip
Project-URL: Issues, https://github.com/mip-org/mip/issues
Keywords: matlab,package-manager
Classifier: Development Status :: 3 - Alpha
Classifier: Intended Audience :: Developers
Classifier: Intended Audience :: Science/Research
Classifier: License :: OSI Approved :: Apache Software License
Classifier: Programming Language :: Python :: 3
Classifier: Programming Language :: Python :: 3.6
Classifier: Programming Language :: Python :: 3.7
Classifier: Programming Language :: Python :: 3.8
Classifier: Programming Language :: Python :: 3.9
Classifier: Programming Language :: Python :: 3.10
Classifier: Programming Language :: Python :: 3.11
Classifier: Topic :: Software Development :: Libraries
Classifier: Topic :: Scientific/Engineering
Requires-Python: >=3.6
License-File: LICENSE
Requires-Dist: requests
Dynamic: license-file
